matHist/__init__.py
matHist/header.py
matHist/matplotlib_hist.py
matHist-0.1.1.dist-info/LICENSE
matHist-0.1.1.dist-info/METADATA
matHist-0.1.1.dist-info/WHEEL
matHist-0.1.1.dist-info/entry_points.txt
matHist-0.1.1.dist-info/top_level.txt
matHist-0.1.1.dist-info/RECORD
