Metadata-Version: 2.1
Name: matHist
Version: 0.1.1
Summary: A Python script to plot normalized histogram using Python3-Matplotlib
Home-page: https://github.com/sumitavakundu007/matHist
Author: Sumitava Kundu
Author-email: kundusumitava@gmail.com
License: UNKNOWN
Project-URL: Bug Reports, https://github.com/sumitavakundu007/matHist/issues
Project-URL: Say Thanks!, http://saythanks.io/to/example
Project-URL: Source, https://github.com/sumitavakundu007/matHist/
Keywords: sample,setuptools,development
Platform: UNKNOWN
Classifier: Intended Audience :: Developers
Classifier: Topic :: Software Development :: Build Tools
Classifier: License :: OSI Approved :: MIT License
Classifier: Programming Language :: Python :: 3
Classifier: Programming Language :: Python :: 3.6
Classifier: Programming Language :: Python :: 3.7
Classifier: Programming Language :: Python :: 3.8
Classifier: Programming Language :: Python :: 3.9
Requires-Python: >=3.6
License-File: LICENSE
Requires-Dist: numpy
Requires-Dist: matplotlib
